exoclasma_pipe/__init__.py
exoclasma_pipe/config.json
exoclasma_pipe/exoclasma_pipe.py
exoclasma_pipe-0.9.1.dist-info/METADATA
exoclasma_pipe-0.9.1.dist-info/WHEEL
exoclasma_pipe-0.9.1.dist-info/entry_points.txt
exoclasma_pipe-0.9.1.dist-info/licenses/LICENSE
exoclasma_pipe-0.9.1.dist-info/RECORD
